{"returnCode":1,"returnCodeDesc":"Success","data":{"lotDetails":{"id":null,"lotNumber":null,"lotAcv":null,"repairCost":null,"auctionDateStr":null,"auctionTimeStr":null,"auctionTime":null,"myMaxBid":0.0,"awardedHighBid":0.0,"rowClass":null,"saleStatus":null,"sealedBidFlag":null,"damageDesc":"Aguardando Classificação","bidStatus":null,"vehicleTypeCode":null,"counterBidStatus":null,"docType":"Aguardando Classificação","saleAmountBIN":"","maxOfferBIN":"","isBIN":null,"isReserved":null,"incrementAmountStr":null,"suggestedOfferAmountStr":null,"incrementAmount":null,"suggestedOfferAmount":null,"isLastVersion":false,"ln":948536,"mkn":"LAND ROVER","lm":"RANGE ROVER SPORT","lcy":2021,"lic":["CERT = 1"],"orr":0.0,"ord":"km","egn":null,"ad":null,"al":null,"bnp":0.0,"hb":0.0,"stt":"Aguardando Classificação","tims":"https://brimages.copart.com.br/Repository/Fotos/d04b08ff-b54c-4ab4-bbbf-1c47364733a0?imageType=thumbnail","dtd":"Aguardando Classificação","sdu":null,"lvbd":null,"currBid":0.0,"ft":"HIBRIDO ELETRICO/GASOLINA","hk":"Y","lss":"NOT_ON_SALE","vehTypDesc":"SUV Grandes","syn":null,"scn":"","phynumb":46,"ynumb":null,"yn":"","aan":0,"bds":"","fv":"","myb":0.0,"version":"RANGE ROVER SPORT P400E PHEV HSE 2.0 INGENIUM TURBO","my":"2021","la":401531.0,"vt":"Aguardando Classificação","lt":"FINANCIAMENTO","drvr":"Motor dá partida e engrena","ldlp":"4","cmmnts":"VEÍCULO COM GARANTIA DE MOTOR E CÂMBIO | VEÍCULO SEM REGISTRO DE LEILÃO E SINISTRO | VEÍCULO BLINDADO, INFORMAÇÃO NÃO CONSTA NO DOCUMENTO, REGULARIZAÇÃO E DESPESAS SERÃO POR CONTA DO COMPRADOR","showtnc":false,"trl":"","scl":"","cuc":"BRL","inc":0.0,"lotSoldFlag":null,"gr":"Vendido/Expedido","pyn":"Itaquaquecetuba - SP","armored":true,"ifs":true}}}