{"returnCode":1,"returnCodeDesc":"Success","data":{"lotDetails":{"id":null,"lotNumber":null,"lotAcv":null,"repairCost":null,"auctionDateStr":null,"auctionTimeStr":null,"auctionTime":null,"myMaxBid":0.0,"awardedHighBid":0.0,"rowClass":null,"saleStatus":null,"sealedBidFlag":null,"damageDesc":"Aguardando Classificação","bidStatus":null,"vehicleTypeCode":null,"counterBidStatus":null,"docType":"Aguardando Classificação","saleAmountBIN":"","maxOfferBIN":"","isBIN":null,"isReserved":null,"incrementAmountStr":null,"suggestedOfferAmountStr":null,"incrementAmount":null,"suggestedOfferAmount":null,"isLastVersion":false,"ln":1014249,"mkn":"ZONTES","lm":"V310","lcy":2024,"lic":["CERT = 1"],"orr":0.0,"ord":"km","egn":null,"ad":null,"al":null,"bnp":0.0,"hb":0.0,"stt":"Aguardando Classificação","tims":"https://brimages.copart.com.br/Repository/Fotos/7092150e-8122-4769-a069-208ac57ccb52?imageType=thumbnail","dtd":"Aguardando Classificação","sdu":null,"lvbd":null,"currBid":0.0,"ft":"Gasolina","hk":"Y","lss":"NOT_ON_SALE","vehTypDesc":"Motos","syn":null,"scn":"","phynumb":53,"ynumb":null,"yn":"","aan":0,"bds":"","fv":"","myb":0.0,"version":"V310 ABS ","my":"2023","la":25075.0,"vt":"Aguardando Classificação","lt":"VMC","drvr":"Motor dá partida e engrena","ldlp":"3","cmmnts":"|VEÍCULO COM REGISTRO DE SINISTRO|||VEÍCULO POSSUÍ HISTÓRICO DE ROUBO/FURTO|VEÍCULO VENDIDO NO ESTADO EM QUE SE ENCONTRA, VISITE O LOTE. PARA MAIS INFORMAÇÕES VIDE O TERMO E CONDIÇÕES GERAIS DE VENDAS E CONDIÇÕES ESPECÍFICAS DO VMC/COMITENTE VENDEDOR.\r\n","showtnc":false,"trl":"","scl":"","cuc":"BRL","inc":0.0,"lotSoldFlag":null,"gr":"VMC - 09","pyn":"Curitiba - PR","armored":false,"ifs":true}}}