{"returnCode":1,"returnCodeDesc":"Success","data":{"imagesList":{"FULL_IMAGE":[{"url":"https://brimages.copart.com.br/Repository/Fotos/b71a2c6e-e0b5-4609-ad47-6b52dcf69e0d?imageType=vga","imageType":"F","sequenceNumber":1,"swiftFlag":false,"imageTypeDescription":"FULL_IMAGE","highRes":true,"ln":720077},{"url":"https://brimages.copart.com.br/Repository/Fotos/7143c697-458c-45d6-80de-03f285158d73?imageType=vga","imageType":"F","sequenceNumber":2,"swiftFlag":false,"imageTypeDescription":"FULL_IMAGE","highRes":true,"ln":720077},{"url":"https://brimages.copart.com.br/Repository/Fotos/028228cf-87e2-41f2-8462-0941ea1eae6b?imageType=vga","imageType":"F","sequenceNumber":3,"swiftFlag":false,"imageTypeDescription":"FULL_IMAGE","highRes":true,"ln":720077},{"url":"https://brimages.copart.com.br/Repository/Fotos/29fdc2c0-8c3e-4399-8bc4-75bffe4962ac?imageType=vga","imageType":"F","sequenceNumber":4,"swiftFlag":false,"imageTypeDescription":"FULL_IMAGE","highRes":true,"ln":720077},{"url":"https://brimages.copart.com.br/Repository/Fotos/a713ad56-7941-490d-8aca-93209838b7ca?imageType=vga","imageType":"F","sequenceNumber":5,"swiftFlag":false,"imageTypeDescription":"FULL_IMAGE","highRes":true,"ln":720077},{"url":"https://brimages.copart.com.br/Repository/Fotos/161b105c-5198-4a42-a656-c6e6216d5874?imageType=vga","imageType":"F","sequenceNumber":6,"swiftFlag":false,"imageTypeDescription":"FULL_IMAGE","highRes":true,"ln":720077},{"url":"https://brimages.copart.com.br/Repository/Fotos/7237ec3c-2ca8-4b9f-a3cd-064e9ef3ac6c?imageType=vga","imageType":"F","sequenceNumber":7,"swiftFlag":false,"imageTypeDescription":"FULL_IMAGE","highRes":true,"ln":720077},{"url":"https://brimages.copart.com.br/Repository/Fotos/a59de61d-9265-4f56-bcb8-33cd533cda52?imageType=vga","imageType":"F","sequenceNumber":8,"swiftFlag":false,"imageTypeDescription":"FULL_IMAGE","highRes":true,"ln":720077},{"url":"https://brimages.copart.com.br/Repository/Fotos/743eda25-a0ab-480b-9dab-4d140050f4b4?imageType=vga","imageType":"F","sequenceNumber":9,"swiftFlag":false,"imageTypeDescription":"FULL_IMAGE","highRes":true,"ln":720077},{"url":"https://brimages.copart.com.br/Repository/Fotos/791b1ac8-7c8d-431a-b201-109469c425d9?imageType=vga","imageType":"F","sequenceNumber":10,"swiftFlag":false,"imageTypeDescription":"FULL_IMAGE","highRes":true,"ln":720077}],"HIGH_RESOLUTION_IMAGE":[{"url":"https://brimages.copart.com.br/Repository/Fotos/b71a2c6e-e0b5-4609-ad47-6b52dcf69e0d","imageType":"O","sequenceNumber":1,"swiftFlag":false,"imageTypeDescription":"HIGH_RESOLUTION_IMAGE","highRes":true,"ln":720077},{"url":"https://brimages.copart.com.br/Repository/Fotos/7143c697-458c-45d6-80de-03f285158d73","imageType":"O","sequenceNumber":2,"swiftFlag":false,"imageTypeDescription":"HIGH_RESOLUTION_IMAGE","highRes":true,"ln":720077},{"url":"https://brimages.copart.com.br/Repository/Fotos/028228cf-87e2-41f2-8462-0941ea1eae6b","imageType":"O","sequenceNumber":3,"swiftFlag":false,"imageTypeDescription":"HIGH_RESOLUTION_IMAGE","highRes":true,"ln":720077},{"url":"https://brimages.copart.com.br/Repository/Fotos/29fdc2c0-8c3e-4399-8bc4-75bffe4962ac","imageType":"O","sequenceNumber":4,"swiftFlag":false,"imageTypeDescription":"HIGH_RESOLUTION_IMAGE","highRes":true,"ln":720077},{"url":"https://brimages.copart.com.br/Repository/Fotos/a713ad56-7941-490d-8aca-93209838b7ca","imageType":"O","sequenceNumber":5,"swiftFlag":false,"imageTypeDescription":"HIGH_RESOLUTION_IMAGE","highRes":true,"ln":720077},{"url":"https://brimages.copart.com.br/Repository/Fotos/161b105c-5198-4a42-a656-c6e6216d5874","imageType":"O","sequenceNumber":6,"swiftFlag":false,"imageTypeDescription":"HIGH_RESOLUTION_IMAGE","highRes":true,"ln":720077},{"url":"https://brimages.copart.com.br/Repository/Fotos/7237ec3c-2ca8-4b9f-a3cd-064e9ef3ac6c","imageType":"O","sequenceNumber":7,"swiftFlag":false,"imageTypeDescription":"HIGH_RESOLUTION_IMAGE","highRes":true,"ln":720077},{"url":"https://brimages.copart.com.br/Repository/Fotos/a59de61d-9265-4f56-bcb8-33cd533cda52","imageType":"O","sequenceNumber":8,"swiftFlag":false,"imageTypeDescription":"HIGH_RESOLUTION_IMAGE","highRes":true,"ln":720077},{"url":"https://brimages.copart.com.br/Repository/Fotos/743eda25-a0ab-480b-9dab-4d140050f4b4","imageType":"O","sequenceNumber":9,"swiftFlag":false,"imageTypeDescription":"HIGH_RESOLUTION_IMAGE","highRes":true,"ln":720077},{"url":"https://brimages.copart.com.br/Repository/Fotos/791b1ac8-7c8d-431a-b201-109469c425d9","imageType":"O","sequenceNumber":10,"swiftFlag":false,"imageTypeDescription":"HIGH_RESOLUTION_IMAGE","highRes":true,"ln":720077}],"THUMBNAIL_IMAGE":[{"url":"https://brimages.copart.com.br/Repository/Fotos/b71a2c6e-e0b5-4609-ad47-6b52dcf69e0d?imageType=thumbnail","imageType":"T","sequenceNumber":1,"swiftFlag":false,"imageTypeDescription":"THUMBNAIL_IMAGE","highRes":false,"ln":720077},{"url":"https://brimages.copart.com.br/Repository/Fotos/7143c697-458c-45d6-80de-03f285158d73?imageType=thumbnail","imageType":"T","sequenceNumber":2,"swiftFlag":false,"imageTypeDescription":"THUMBNAIL_IMAGE","highRes":false,"ln":720077},{"url":"https://brimages.copart.com.br/Repository/Fotos/028228cf-87e2-41f2-8462-0941ea1eae6b?imageType=thumbnail","imageType":"T","sequenceNumber":3,"swiftFlag":false,"imageTypeDescription":"THUMBNAIL_IMAGE","highRes":false,"ln":720077},{"url":"https://brimages.copart.com.br/Repository/Fotos/29fdc2c0-8c3e-4399-8bc4-75bffe4962ac?imageType=thumbnail","imageType":"T","sequenceNumber":4,"swiftFlag":false,"imageTypeDescription":"THUMBNAIL_IMAGE","highRes":false,"ln":720077},{"url":"https://brimages.copart.com.br/Repository/Fotos/a713ad56-7941-490d-8aca-93209838b7ca?imageType=thumbnail","imageType":"T","sequenceNumber":5,"swiftFlag":false,"imageTypeDescription":"THUMBNAIL_IMAGE","highRes":false,"ln":720077},{"url":"https://brimages.copart.com.br/Repository/Fotos/161b105c-5198-4a42-a656-c6e6216d5874?imageType=thumbnail","imageType":"T","sequenceNumber":6,"swiftFlag":false,"imageTypeDescription":"THUMBNAIL_IMAGE","highRes":false,"ln":720077},{"url":"https://brimages.copart.com.br/Repository/Fotos/7237ec3c-2ca8-4b9f-a3cd-064e9ef3ac6c?imageType=thumbnail","imageType":"T","sequenceNumber":7,"swiftFlag":false,"imageTypeDescription":"THUMBNAIL_IMAGE","highRes":false,"ln":720077},{"url":"https://brimages.copart.com.br/Repository/Fotos/a59de61d-9265-4f56-bcb8-33cd533cda52?imageType=thumbnail","imageType":"T","sequenceNumber":8,"swiftFlag":false,"imageTypeDescription":"THUMBNAIL_IMAGE","highRes":false,"ln":720077},{"url":"https://brimages.copart.com.br/Repository/Fotos/743eda25-a0ab-480b-9dab-4d140050f4b4?imageType=thumbnail","imageType":"T","sequenceNumber":9,"swiftFlag":false,"imageTypeDescription":"THUMBNAIL_IMAGE","highRes":false,"ln":720077},{"url":"https://brimages.copart.com.br/Repository/Fotos/791b1ac8-7c8d-431a-b201-109469c425d9?imageType=thumbnail","imageType":"T","sequenceNumber":10,"swiftFlag":false,"imageTypeDescription":"THUMBNAIL_IMAGE","highRes":false,"ln":720077}]}}}