{"returnCode":1,"returnCodeDesc":"Success","data":{"imagesList":{"FULL_IMAGE":[{"url":"https://brimages.copart.com.br/Repository/Fotos/fb797396-20dd-4bff-9330-d859250bdf2c?imageType=vga","imageType":"F","sequenceNumber":1,"swiftFlag":false,"imageTypeDescription":"FULL_IMAGE","highRes":true,"ln":849927},{"url":"https://brimages.copart.com.br/Repository/Fotos/23105c70-4a8b-4327-be49-07cad908b3a7?imageType=vga","imageType":"F","sequenceNumber":2,"swiftFlag":false,"imageTypeDescription":"FULL_IMAGE","highRes":true,"ln":849927},{"url":"https://brimages.copart.com.br/Repository/Fotos/8658397d-4f2e-4fd7-8ccc-c1a71be2b013?imageType=vga","imageType":"F","sequenceNumber":3,"swiftFlag":false,"imageTypeDescription":"FULL_IMAGE","highRes":true,"ln":849927},{"url":"https://brimages.copart.com.br/Repository/Fotos/d1ba0061-f159-47cb-8e8d-260a7def6899?imageType=vga","imageType":"F","sequenceNumber":4,"swiftFlag":false,"imageTypeDescription":"FULL_IMAGE","highRes":true,"ln":849927},{"url":"https://brimages.copart.com.br/Repository/Fotos/3b056dc4-4250-4682-98d0-548ca2cb6f02?imageType=vga","imageType":"F","sequenceNumber":5,"swiftFlag":false,"imageTypeDescription":"FULL_IMAGE","highRes":true,"ln":849927},{"url":"https://brimages.copart.com.br/Repository/Fotos/172bd35e-0d5a-4294-8e95-87f3cdabffff?imageType=vga","imageType":"F","sequenceNumber":6,"swiftFlag":false,"imageTypeDescription":"FULL_IMAGE","highRes":true,"ln":849927},{"url":"https://brimages.copart.com.br/Repository/Fotos/eb84265d-d9ee-4af1-ba51-92d8e4b3c412?imageType=vga","imageType":"F","sequenceNumber":7,"swiftFlag":false,"imageTypeDescription":"FULL_IMAGE","highRes":true,"ln":849927},{"url":"https://brimages.copart.com.br/Repository/Fotos/43b22468-1a6f-4b99-b4d5-6e10965298ed?imageType=vga","imageType":"F","sequenceNumber":8,"swiftFlag":false,"imageTypeDescription":"FULL_IMAGE","highRes":true,"ln":849927},{"url":"https://brimages.copart.com.br/Repository/Fotos/94e7f6bf-f0fd-4ed2-be75-2a4b924b817f?imageType=vga","imageType":"F","sequenceNumber":9,"swiftFlag":false,"imageTypeDescription":"FULL_IMAGE","highRes":true,"ln":849927},{"url":"https://brimages.copart.com.br/Repository/Fotos/039ed34b-f94e-40e1-b764-d6309fc9822c?imageType=vga","imageType":"F","sequenceNumber":10,"swiftFlag":false,"imageTypeDescription":"FULL_IMAGE","highRes":true,"ln":849927}],"THUMBNAIL_IMAGE":[{"url":"https://brimages.copart.com.br/Repository/Fotos/fb797396-20dd-4bff-9330-d859250bdf2c?imageType=thumbnail","imageType":"T","sequenceNumber":1,"swiftFlag":false,"imageTypeDescription":"THUMBNAIL_IMAGE","highRes":false,"ln":849927},{"url":"https://brimages.copart.com.br/Repository/Fotos/23105c70-4a8b-4327-be49-07cad908b3a7?imageType=thumbnail","imageType":"T","sequenceNumber":2,"swiftFlag":false,"imageTypeDescription":"THUMBNAIL_IMAGE","highRes":false,"ln":849927},{"url":"https://brimages.copart.com.br/Repository/Fotos/8658397d-4f2e-4fd7-8ccc-c1a71be2b013?imageType=thumbnail","imageType":"T","sequenceNumber":3,"swiftFlag":false,"imageTypeDescription":"THUMBNAIL_IMAGE","highRes":false,"ln":849927},{"url":"https://brimages.copart.com.br/Repository/Fotos/d1ba0061-f159-47cb-8e8d-260a7def6899?imageType=thumbnail","imageType":"T","sequenceNumber":4,"swiftFlag":false,"imageTypeDescription":"THUMBNAIL_IMAGE","highRes":false,"ln":849927},{"url":"https://brimages.copart.com.br/Repository/Fotos/3b056dc4-4250-4682-98d0-548ca2cb6f02?imageType=thumbnail","imageType":"T","sequenceNumber":5,"swiftFlag":false,"imageTypeDescription":"THUMBNAIL_IMAGE","highRes":false,"ln":849927},{"url":"https://brimages.copart.com.br/Repository/Fotos/172bd35e-0d5a-4294-8e95-87f3cdabffff?imageType=thumbnail","imageType":"T","sequenceNumber":6,"swiftFlag":false,"imageTypeDescription":"THUMBNAIL_IMAGE","highRes":false,"ln":849927},{"url":"https://brimages.copart.com.br/Repository/Fotos/eb84265d-d9ee-4af1-ba51-92d8e4b3c412?imageType=thumbnail","imageType":"T","sequenceNumber":7,"swiftFlag":false,"imageTypeDescription":"THUMBNAIL_IMAGE","highRes":false,"ln":849927},{"url":"https://brimages.copart.com.br/Repository/Fotos/43b22468-1a6f-4b99-b4d5-6e10965298ed?imageType=thumbnail","imageType":"T","sequenceNumber":8,"swiftFlag":false,"imageTypeDescription":"THUMBNAIL_IMAGE","highRes":false,"ln":849927},{"url":"https://brimages.copart.com.br/Repository/Fotos/94e7f6bf-f0fd-4ed2-be75-2a4b924b817f?imageType=thumbnail","imageType":"T","sequenceNumber":9,"swiftFlag":false,"imageTypeDescription":"THUMBNAIL_IMAGE","highRes":false,"ln":849927},{"url":"https://brimages.copart.com.br/Repository/Fotos/039ed34b-f94e-40e1-b764-d6309fc9822c?imageType=thumbnail","imageType":"T","sequenceNumber":10,"swiftFlag":false,"imageTypeDescription":"THUMBNAIL_IMAGE","highRes":false,"ln":849927}],"HIGH_RESOLUTION_IMAGE":[{"url":"https://brimages.copart.com.br/Repository/Fotos/fb797396-20dd-4bff-9330-d859250bdf2c","imageType":"O","sequenceNumber":1,"swiftFlag":false,"imageTypeDescription":"HIGH_RESOLUTION_IMAGE","highRes":true,"ln":849927},{"url":"https://brimages.copart.com.br/Repository/Fotos/23105c70-4a8b-4327-be49-07cad908b3a7","imageType":"O","sequenceNumber":2,"swiftFlag":false,"imageTypeDescription":"HIGH_RESOLUTION_IMAGE","highRes":true,"ln":849927},{"url":"https://brimages.copart.com.br/Repository/Fotos/8658397d-4f2e-4fd7-8ccc-c1a71be2b013","imageType":"O","sequenceNumber":3,"swiftFlag":false,"imageTypeDescription":"HIGH_RESOLUTION_IMAGE","highRes":true,"ln":849927},{"url":"https://brimages.copart.com.br/Repository/Fotos/d1ba0061-f159-47cb-8e8d-260a7def6899","imageType":"O","sequenceNumber":4,"swiftFlag":false,"imageTypeDescription":"HIGH_RESOLUTION_IMAGE","highRes":true,"ln":849927},{"url":"https://brimages.copart.com.br/Repository/Fotos/3b056dc4-4250-4682-98d0-548ca2cb6f02","imageType":"O","sequenceNumber":5,"swiftFlag":false,"imageTypeDescription":"HIGH_RESOLUTION_IMAGE","highRes":true,"ln":849927},{"url":"https://brimages.copart.com.br/Repository/Fotos/172bd35e-0d5a-4294-8e95-87f3cdabffff","imageType":"O","sequenceNumber":6,"swiftFlag":false,"imageTypeDescription":"HIGH_RESOLUTION_IMAGE","highRes":true,"ln":849927},{"url":"https://brimages.copart.com.br/Repository/Fotos/eb84265d-d9ee-4af1-ba51-92d8e4b3c412","imageType":"O","sequenceNumber":7,"swiftFlag":false,"imageTypeDescription":"HIGH_RESOLUTION_IMAGE","highRes":true,"ln":849927},{"url":"https://brimages.copart.com.br/Repository/Fotos/43b22468-1a6f-4b99-b4d5-6e10965298ed","imageType":"O","sequenceNumber":8,"swiftFlag":false,"imageTypeDescription":"HIGH_RESOLUTION_IMAGE","highRes":true,"ln":849927},{"url":"https://brimages.copart.com.br/Repository/Fotos/94e7f6bf-f0fd-4ed2-be75-2a4b924b817f","imageType":"O","sequenceNumber":9,"swiftFlag":false,"imageTypeDescription":"HIGH_RESOLUTION_IMAGE","highRes":true,"ln":849927},{"url":"https://brimages.copart.com.br/Repository/Fotos/039ed34b-f94e-40e1-b764-d6309fc9822c","imageType":"O","sequenceNumber":10,"swiftFlag":false,"imageTypeDescription":"HIGH_RESOLUTION_IMAGE","highRes":true,"ln":849927}]}}}