{"returnCode":1,"returnCodeDesc":"Success","data":{"imagesList":{"FULL_IMAGE":[{"url":"https://brimages.copart.com.br/Repository/Fotos/f37e46b5-3c21-408c-ae5b-13e5f3f11f9c?imageType=vga","imageType":"F","sequenceNumber":1,"swiftFlag":false,"imageTypeDescription":"FULL_IMAGE","highRes":true,"ln":1006307},{"url":"https://brimages.copart.com.br/Repository/Fotos/6e09a93b-2f97-4037-8ca5-876e61567246?imageType=vga","imageType":"F","sequenceNumber":2,"swiftFlag":false,"imageTypeDescription":"FULL_IMAGE","highRes":true,"ln":1006307},{"url":"https://brimages.copart.com.br/Repository/Fotos/8211e6ac-1812-4121-b816-df61fdb67e19?imageType=vga","imageType":"F","sequenceNumber":3,"swiftFlag":false,"imageTypeDescription":"FULL_IMAGE","highRes":true,"ln":1006307},{"url":"https://brimages.copart.com.br/Repository/Fotos/681055a3-82e9-492f-b15d-4fcdbfad5139?imageType=vga","imageType":"F","sequenceNumber":4,"swiftFlag":false,"imageTypeDescription":"FULL_IMAGE","highRes":true,"ln":1006307},{"url":"https://brimages.copart.com.br/Repository/Fotos/4af17775-72f8-4dea-8713-6e94f8e47bd9?imageType=vga","imageType":"F","sequenceNumber":5,"swiftFlag":false,"imageTypeDescription":"FULL_IMAGE","highRes":true,"ln":1006307},{"url":"https://brimages.copart.com.br/Repository/Fotos/f73f3708-e481-4710-b633-06de651e04ec?imageType=vga","imageType":"F","sequenceNumber":6,"swiftFlag":false,"imageTypeDescription":"FULL_IMAGE","highRes":true,"ln":1006307},{"url":"https://brimages.copart.com.br/Repository/Fotos/a15e91d3-5052-4de3-9eb3-d74cec6d2b96?imageType=vga","imageType":"F","sequenceNumber":7,"swiftFlag":false,"imageTypeDescription":"FULL_IMAGE","highRes":true,"ln":1006307},{"url":"https://brimages.copart.com.br/Repository/Fotos/7d09935a-15b7-404f-873b-8843e9e3f479?imageType=vga","imageType":"F","sequenceNumber":8,"swiftFlag":false,"imageTypeDescription":"FULL_IMAGE","highRes":true,"ln":1006307},{"url":"https://brimages.copart.com.br/Repository/Fotos/1b1ae691-4179-4dd0-aa0d-d2749abb11d3?imageType=vga","imageType":"F","sequenceNumber":9,"swiftFlag":false,"imageTypeDescription":"FULL_IMAGE","highRes":true,"ln":1006307},{"url":"https://brimages.copart.com.br/Repository/Fotos/dd3ee24b-7ffd-4bd4-a9ec-70704e9f504f?imageType=vga","imageType":"F","sequenceNumber":10,"swiftFlag":false,"imageTypeDescription":"FULL_IMAGE","highRes":true,"ln":1006307},{"url":"https://brimages.copart.com.br/Repository/Fotos/79e2bc23-ecd3-4b25-9fc2-e513c010bc0b?imageType=vga","imageType":"F","sequenceNumber":11,"swiftFlag":false,"imageTypeDescription":"FULL_IMAGE","highRes":true,"ln":1006307},{"url":"https://brimages.copart.com.br/Repository/Fotos/cf6f0a8f-ecb9-4338-85f0-f4af53fdde9b?imageType=vga","imageType":"F","sequenceNumber":12,"swiftFlag":false,"imageTypeDescription":"FULL_IMAGE","highRes":true,"ln":1006307}],"THUMBNAIL_IMAGE":[{"url":"https://brimages.copart.com.br/Repository/Fotos/f37e46b5-3c21-408c-ae5b-13e5f3f11f9c?imageType=thumbnail","imageType":"T","sequenceNumber":1,"swiftFlag":false,"imageTypeDescription":"THUMBNAIL_IMAGE","highRes":false,"ln":1006307},{"url":"https://brimages.copart.com.br/Repository/Fotos/6e09a93b-2f97-4037-8ca5-876e61567246?imageType=thumbnail","imageType":"T","sequenceNumber":2,"swiftFlag":false,"imageTypeDescription":"THUMBNAIL_IMAGE","highRes":false,"ln":1006307},{"url":"https://brimages.copart.com.br/Repository/Fotos/8211e6ac-1812-4121-b816-df61fdb67e19?imageType=thumbnail","imageType":"T","sequenceNumber":3,"swiftFlag":false,"imageTypeDescription":"THUMBNAIL_IMAGE","highRes":false,"ln":1006307},{"url":"https://brimages.copart.com.br/Repository/Fotos/681055a3-82e9-492f-b15d-4fcdbfad5139?imageType=thumbnail","imageType":"T","sequenceNumber":4,"swiftFlag":false,"imageTypeDescription":"THUMBNAIL_IMAGE","highRes":false,"ln":1006307},{"url":"https://brimages.copart.com.br/Repository/Fotos/4af17775-72f8-4dea-8713-6e94f8e47bd9?imageType=thumbnail","imageType":"T","sequenceNumber":5,"swiftFlag":false,"imageTypeDescription":"THUMBNAIL_IMAGE","highRes":false,"ln":1006307},{"url":"https://brimages.copart.com.br/Repository/Fotos/f73f3708-e481-4710-b633-06de651e04ec?imageType=thumbnail","imageType":"T","sequenceNumber":6,"swiftFlag":false,"imageTypeDescription":"THUMBNAIL_IMAGE","highRes":false,"ln":1006307},{"url":"https://brimages.copart.com.br/Repository/Fotos/a15e91d3-5052-4de3-9eb3-d74cec6d2b96?imageType=thumbnail","imageType":"T","sequenceNumber":7,"swiftFlag":false,"imageTypeDescription":"THUMBNAIL_IMAGE","highRes":false,"ln":1006307},{"url":"https://brimages.copart.com.br/Repository/Fotos/7d09935a-15b7-404f-873b-8843e9e3f479?imageType=thumbnail","imageType":"T","sequenceNumber":8,"swiftFlag":false,"imageTypeDescription":"THUMBNAIL_IMAGE","highRes":false,"ln":1006307},{"url":"https://brimages.copart.com.br/Repository/Fotos/1b1ae691-4179-4dd0-aa0d-d2749abb11d3?imageType=thumbnail","imageType":"T","sequenceNumber":9,"swiftFlag":false,"imageTypeDescription":"THUMBNAIL_IMAGE","highRes":false,"ln":1006307},{"url":"https://brimages.copart.com.br/Repository/Fotos/dd3ee24b-7ffd-4bd4-a9ec-70704e9f504f?imageType=thumbnail","imageType":"T","sequenceNumber":10,"swiftFlag":false,"imageTypeDescription":"THUMBNAIL_IMAGE","highRes":false,"ln":1006307},{"url":"https://brimages.copart.com.br/Repository/Fotos/79e2bc23-ecd3-4b25-9fc2-e513c010bc0b?imageType=thumbnail","imageType":"T","sequenceNumber":11,"swiftFlag":false,"imageTypeDescription":"THUMBNAIL_IMAGE","highRes":false,"ln":1006307},{"url":"https://brimages.copart.com.br/Repository/Fotos/cf6f0a8f-ecb9-4338-85f0-f4af53fdde9b?imageType=thumbnail","imageType":"T","sequenceNumber":12,"swiftFlag":false,"imageTypeDescription":"THUMBNAIL_IMAGE","highRes":false,"ln":1006307}],"HIGH_RESOLUTION_IMAGE":[{"url":"https://brimages.copart.com.br/Repository/Fotos/f37e46b5-3c21-408c-ae5b-13e5f3f11f9c","imageType":"O","sequenceNumber":1,"swiftFlag":false,"imageTypeDescription":"HIGH_RESOLUTION_IMAGE","highRes":true,"ln":1006307},{"url":"https://brimages.copart.com.br/Repository/Fotos/6e09a93b-2f97-4037-8ca5-876e61567246","imageType":"O","sequenceNumber":2,"swiftFlag":false,"imageTypeDescription":"HIGH_RESOLUTION_IMAGE","highRes":true,"ln":1006307},{"url":"https://brimages.copart.com.br/Repository/Fotos/8211e6ac-1812-4121-b816-df61fdb67e19","imageType":"O","sequenceNumber":3,"swiftFlag":false,"imageTypeDescription":"HIGH_RESOLUTION_IMAGE","highRes":true,"ln":1006307},{"url":"https://brimages.copart.com.br/Repository/Fotos/681055a3-82e9-492f-b15d-4fcdbfad5139","imageType":"O","sequenceNumber":4,"swiftFlag":false,"imageTypeDescription":"HIGH_RESOLUTION_IMAGE","highRes":true,"ln":1006307},{"url":"https://brimages.copart.com.br/Repository/Fotos/4af17775-72f8-4dea-8713-6e94f8e47bd9","imageType":"O","sequenceNumber":5,"swiftFlag":false,"imageTypeDescription":"HIGH_RESOLUTION_IMAGE","highRes":true,"ln":1006307},{"url":"https://brimages.copart.com.br/Repository/Fotos/f73f3708-e481-4710-b633-06de651e04ec","imageType":"O","sequenceNumber":6,"swiftFlag":false,"imageTypeDescription":"HIGH_RESOLUTION_IMAGE","highRes":true,"ln":1006307},{"url":"https://brimages.copart.com.br/Repository/Fotos/a15e91d3-5052-4de3-9eb3-d74cec6d2b96","imageType":"O","sequenceNumber":7,"swiftFlag":false,"imageTypeDescription":"HIGH_RESOLUTION_IMAGE","highRes":true,"ln":1006307},{"url":"https://brimages.copart.com.br/Repository/Fotos/7d09935a-15b7-404f-873b-8843e9e3f479","imageType":"O","sequenceNumber":8,"swiftFlag":false,"imageTypeDescription":"HIGH_RESOLUTION_IMAGE","highRes":true,"ln":1006307},{"url":"https://brimages.copart.com.br/Repository/Fotos/1b1ae691-4179-4dd0-aa0d-d2749abb11d3","imageType":"O","sequenceNumber":9,"swiftFlag":false,"imageTypeDescription":"HIGH_RESOLUTION_IMAGE","highRes":true,"ln":1006307},{"url":"https://brimages.copart.com.br/Repository/Fotos/dd3ee24b-7ffd-4bd4-a9ec-70704e9f504f","imageType":"O","sequenceNumber":10,"swiftFlag":false,"imageTypeDescription":"HIGH_RESOLUTION_IMAGE","highRes":true,"ln":1006307},{"url":"https://brimages.copart.com.br/Repository/Fotos/79e2bc23-ecd3-4b25-9fc2-e513c010bc0b","imageType":"O","sequenceNumber":11,"swiftFlag":false,"imageTypeDescription":"HIGH_RESOLUTION_IMAGE","highRes":true,"ln":1006307},{"url":"https://brimages.copart.com.br/Repository/Fotos/cf6f0a8f-ecb9-4338-85f0-f4af53fdde9b","imageType":"O","sequenceNumber":12,"swiftFlag":false,"imageTypeDescription":"HIGH_RESOLUTION_IMAGE","highRes":true,"ln":1006307}]}}}