{"returnCode":1,"returnCodeDesc":"Success","data":{"imagesList":{"FULL_IMAGE":[{"url":"https://brimages.copart.com.br/Repository/Fotos/2572985d-78e1-4566-bb7a-0af76966c17e?imageType=vga","imageType":"F","sequenceNumber":1,"swiftFlag":false,"imageTypeDescription":"FULL_IMAGE","highRes":true,"ln":919665},{"url":"https://brimages.copart.com.br/Repository/Fotos/bb758c05-19f1-4b46-83ec-992212a1fdc7?imageType=vga","imageType":"F","sequenceNumber":2,"swiftFlag":false,"imageTypeDescription":"FULL_IMAGE","highRes":true,"ln":919665},{"url":"https://brimages.copart.com.br/Repository/Fotos/9a136d86-ff75-417d-ba2a-c57840ebae77?imageType=vga","imageType":"F","sequenceNumber":3,"swiftFlag":false,"imageTypeDescription":"FULL_IMAGE","highRes":true,"ln":919665},{"url":"https://brimages.copart.com.br/Repository/Fotos/8a3bbc96-a7b7-4fa8-b911-5c4d5e7a396c?imageType=vga","imageType":"F","sequenceNumber":4,"swiftFlag":false,"imageTypeDescription":"FULL_IMAGE","highRes":true,"ln":919665},{"url":"https://brimages.copart.com.br/Repository/Fotos/cbb10ba0-c0d6-4e5e-b57a-4d3acb91b863?imageType=vga","imageType":"F","sequenceNumber":5,"swiftFlag":false,"imageTypeDescription":"FULL_IMAGE","highRes":true,"ln":919665},{"url":"https://brimages.copart.com.br/Repository/Fotos/a8af40e7-ebde-45d8-890c-f46204e7ea80?imageType=vga","imageType":"F","sequenceNumber":6,"swiftFlag":false,"imageTypeDescription":"FULL_IMAGE","highRes":true,"ln":919665},{"url":"https://brimages.copart.com.br/Repository/Fotos/e9e1d939-e689-4bc1-ac4b-ad67b2873626?imageType=vga","imageType":"F","sequenceNumber":7,"swiftFlag":false,"imageTypeDescription":"FULL_IMAGE","highRes":true,"ln":919665},{"url":"https://brimages.copart.com.br/Repository/Fotos/2855bf6e-d087-4814-b015-bbb8ee180941?imageType=vga","imageType":"F","sequenceNumber":8,"swiftFlag":false,"imageTypeDescription":"FULL_IMAGE","highRes":true,"ln":919665},{"url":"https://brimages.copart.com.br/Repository/Fotos/4890b621-758d-443d-8faa-24dbdac783d4?imageType=vga","imageType":"F","sequenceNumber":9,"swiftFlag":false,"imageTypeDescription":"FULL_IMAGE","highRes":true,"ln":919665},{"url":"https://brimages.copart.com.br/Repository/Fotos/5614f871-2cab-48df-8b7e-3ade92cff80f?imageType=vga","imageType":"F","sequenceNumber":10,"swiftFlag":false,"imageTypeDescription":"FULL_IMAGE","highRes":true,"ln":919665}],"HIGH_RESOLUTION_IMAGE":[{"url":"https://brimages.copart.com.br/Repository/Fotos/2572985d-78e1-4566-bb7a-0af76966c17e","imageType":"O","sequenceNumber":1,"swiftFlag":false,"imageTypeDescription":"HIGH_RESOLUTION_IMAGE","highRes":true,"ln":919665},{"url":"https://brimages.copart.com.br/Repository/Fotos/bb758c05-19f1-4b46-83ec-992212a1fdc7","imageType":"O","sequenceNumber":2,"swiftFlag":false,"imageTypeDescription":"HIGH_RESOLUTION_IMAGE","highRes":true,"ln":919665},{"url":"https://brimages.copart.com.br/Repository/Fotos/9a136d86-ff75-417d-ba2a-c57840ebae77","imageType":"O","sequenceNumber":3,"swiftFlag":false,"imageTypeDescription":"HIGH_RESOLUTION_IMAGE","highRes":true,"ln":919665},{"url":"https://brimages.copart.com.br/Repository/Fotos/8a3bbc96-a7b7-4fa8-b911-5c4d5e7a396c","imageType":"O","sequenceNumber":4,"swiftFlag":false,"imageTypeDescription":"HIGH_RESOLUTION_IMAGE","highRes":true,"ln":919665},{"url":"https://brimages.copart.com.br/Repository/Fotos/cbb10ba0-c0d6-4e5e-b57a-4d3acb91b863","imageType":"O","sequenceNumber":5,"swiftFlag":false,"imageTypeDescription":"HIGH_RESOLUTION_IMAGE","highRes":true,"ln":919665},{"url":"https://brimages.copart.com.br/Repository/Fotos/a8af40e7-ebde-45d8-890c-f46204e7ea80","imageType":"O","sequenceNumber":6,"swiftFlag":false,"imageTypeDescription":"HIGH_RESOLUTION_IMAGE","highRes":true,"ln":919665},{"url":"https://brimages.copart.com.br/Repository/Fotos/e9e1d939-e689-4bc1-ac4b-ad67b2873626","imageType":"O","sequenceNumber":7,"swiftFlag":false,"imageTypeDescription":"HIGH_RESOLUTION_IMAGE","highRes":true,"ln":919665},{"url":"https://brimages.copart.com.br/Repository/Fotos/2855bf6e-d087-4814-b015-bbb8ee180941","imageType":"O","sequenceNumber":8,"swiftFlag":false,"imageTypeDescription":"HIGH_RESOLUTION_IMAGE","highRes":true,"ln":919665},{"url":"https://brimages.copart.com.br/Repository/Fotos/4890b621-758d-443d-8faa-24dbdac783d4","imageType":"O","sequenceNumber":9,"swiftFlag":false,"imageTypeDescription":"HIGH_RESOLUTION_IMAGE","highRes":true,"ln":919665},{"url":"https://brimages.copart.com.br/Repository/Fotos/5614f871-2cab-48df-8b7e-3ade92cff80f","imageType":"O","sequenceNumber":10,"swiftFlag":false,"imageTypeDescription":"HIGH_RESOLUTION_IMAGE","highRes":true,"ln":919665}],"THUMBNAIL_IMAGE":[{"url":"https://brimages.copart.com.br/Repository/Fotos/2572985d-78e1-4566-bb7a-0af76966c17e?imageType=thumbnail","imageType":"T","sequenceNumber":1,"swiftFlag":false,"imageTypeDescription":"THUMBNAIL_IMAGE","highRes":false,"ln":919665},{"url":"https://brimages.copart.com.br/Repository/Fotos/bb758c05-19f1-4b46-83ec-992212a1fdc7?imageType=thumbnail","imageType":"T","sequenceNumber":2,"swiftFlag":false,"imageTypeDescription":"THUMBNAIL_IMAGE","highRes":false,"ln":919665},{"url":"https://brimages.copart.com.br/Repository/Fotos/9a136d86-ff75-417d-ba2a-c57840ebae77?imageType=thumbnail","imageType":"T","sequenceNumber":3,"swiftFlag":false,"imageTypeDescription":"THUMBNAIL_IMAGE","highRes":false,"ln":919665},{"url":"https://brimages.copart.com.br/Repository/Fotos/8a3bbc96-a7b7-4fa8-b911-5c4d5e7a396c?imageType=thumbnail","imageType":"T","sequenceNumber":4,"swiftFlag":false,"imageTypeDescription":"THUMBNAIL_IMAGE","highRes":false,"ln":919665},{"url":"https://brimages.copart.com.br/Repository/Fotos/cbb10ba0-c0d6-4e5e-b57a-4d3acb91b863?imageType=thumbnail","imageType":"T","sequenceNumber":5,"swiftFlag":false,"imageTypeDescription":"THUMBNAIL_IMAGE","highRes":false,"ln":919665},{"url":"https://brimages.copart.com.br/Repository/Fotos/a8af40e7-ebde-45d8-890c-f46204e7ea80?imageType=thumbnail","imageType":"T","sequenceNumber":6,"swiftFlag":false,"imageTypeDescription":"THUMBNAIL_IMAGE","highRes":false,"ln":919665},{"url":"https://brimages.copart.com.br/Repository/Fotos/e9e1d939-e689-4bc1-ac4b-ad67b2873626?imageType=thumbnail","imageType":"T","sequenceNumber":7,"swiftFlag":false,"imageTypeDescription":"THUMBNAIL_IMAGE","highRes":false,"ln":919665},{"url":"https://brimages.copart.com.br/Repository/Fotos/2855bf6e-d087-4814-b015-bbb8ee180941?imageType=thumbnail","imageType":"T","sequenceNumber":8,"swiftFlag":false,"imageTypeDescription":"THUMBNAIL_IMAGE","highRes":false,"ln":919665},{"url":"https://brimages.copart.com.br/Repository/Fotos/4890b621-758d-443d-8faa-24dbdac783d4?imageType=thumbnail","imageType":"T","sequenceNumber":9,"swiftFlag":false,"imageTypeDescription":"THUMBNAIL_IMAGE","highRes":false,"ln":919665},{"url":"https://brimages.copart.com.br/Repository/Fotos/5614f871-2cab-48df-8b7e-3ade92cff80f?imageType=thumbnail","imageType":"T","sequenceNumber":10,"swiftFlag":false,"imageTypeDescription":"THUMBNAIL_IMAGE","highRes":false,"ln":919665}]}}}