{"returnCode":1,"returnCodeDesc":"Success","data":{"imagesList":{"FULL_IMAGE":[{"url":"https://brimages.copart.com.br/Repository/Fotos/a0b0c6e4-6cb8-49ed-a1ea-6eb573f31a36?imageType=vga","imageType":"F","sequenceNumber":1,"swiftFlag":false,"imageTypeDescription":"FULL_IMAGE","highRes":true,"ln":992250},{"url":"https://brimages.copart.com.br/Repository/Fotos/0e96f28b-03f3-483a-969a-a442d4c6700f?imageType=vga","imageType":"F","sequenceNumber":2,"swiftFlag":false,"imageTypeDescription":"FULL_IMAGE","highRes":true,"ln":992250},{"url":"https://brimages.copart.com.br/Repository/Fotos/bef071aa-5500-4232-9dd3-4589cbb7b2ac?imageType=vga","imageType":"F","sequenceNumber":3,"swiftFlag":false,"imageTypeDescription":"FULL_IMAGE","highRes":true,"ln":992250},{"url":"https://brimages.copart.com.br/Repository/Fotos/9e741e41-18a1-4aca-92be-dee9825ac2e0?imageType=vga","imageType":"F","sequenceNumber":4,"swiftFlag":false,"imageTypeDescription":"FULL_IMAGE","highRes":true,"ln":992250},{"url":"https://brimages.copart.com.br/Repository/Fotos/ff04a23b-0e78-4d94-a2a1-4fd376246495?imageType=vga","imageType":"F","sequenceNumber":5,"swiftFlag":false,"imageTypeDescription":"FULL_IMAGE","highRes":true,"ln":992250},{"url":"https://brimages.copart.com.br/Repository/Fotos/389a670a-f7fd-429e-88d6-6cb914807f1e?imageType=vga","imageType":"F","sequenceNumber":6,"swiftFlag":false,"imageTypeDescription":"FULL_IMAGE","highRes":true,"ln":992250},{"url":"https://brimages.copart.com.br/Repository/Fotos/3100ec30-925f-4292-81ee-1706366af0d8?imageType=vga","imageType":"F","sequenceNumber":7,"swiftFlag":false,"imageTypeDescription":"FULL_IMAGE","highRes":true,"ln":992250},{"url":"https://brimages.copart.com.br/Repository/Fotos/7d6ed11d-a220-4409-9ee9-4c78426df185?imageType=vga","imageType":"F","sequenceNumber":8,"swiftFlag":false,"imageTypeDescription":"FULL_IMAGE","highRes":true,"ln":992250},{"url":"https://brimages.copart.com.br/Repository/Fotos/5a79c63e-5f3f-4ced-adcc-713475c7bd31?imageType=vga","imageType":"F","sequenceNumber":9,"swiftFlag":false,"imageTypeDescription":"FULL_IMAGE","highRes":true,"ln":992250},{"url":"https://brimages.copart.com.br/Repository/Fotos/34bc9860-fadf-46a2-a283-365002140abc?imageType=vga","imageType":"F","sequenceNumber":10,"swiftFlag":false,"imageTypeDescription":"FULL_IMAGE","highRes":true,"ln":992250}],"THUMBNAIL_IMAGE":[{"url":"https://brimages.copart.com.br/Repository/Fotos/a0b0c6e4-6cb8-49ed-a1ea-6eb573f31a36?imageType=thumbnail","imageType":"T","sequenceNumber":1,"swiftFlag":false,"imageTypeDescription":"THUMBNAIL_IMAGE","highRes":false,"ln":992250},{"url":"https://brimages.copart.com.br/Repository/Fotos/0e96f28b-03f3-483a-969a-a442d4c6700f?imageType=thumbnail","imageType":"T","sequenceNumber":2,"swiftFlag":false,"imageTypeDescription":"THUMBNAIL_IMAGE","highRes":false,"ln":992250},{"url":"https://brimages.copart.com.br/Repository/Fotos/bef071aa-5500-4232-9dd3-4589cbb7b2ac?imageType=thumbnail","imageType":"T","sequenceNumber":3,"swiftFlag":false,"imageTypeDescription":"THUMBNAIL_IMAGE","highRes":false,"ln":992250},{"url":"https://brimages.copart.com.br/Repository/Fotos/9e741e41-18a1-4aca-92be-dee9825ac2e0?imageType=thumbnail","imageType":"T","sequenceNumber":4,"swiftFlag":false,"imageTypeDescription":"THUMBNAIL_IMAGE","highRes":false,"ln":992250},{"url":"https://brimages.copart.com.br/Repository/Fotos/ff04a23b-0e78-4d94-a2a1-4fd376246495?imageType=thumbnail","imageType":"T","sequenceNumber":5,"swiftFlag":false,"imageTypeDescription":"THUMBNAIL_IMAGE","highRes":false,"ln":992250},{"url":"https://brimages.copart.com.br/Repository/Fotos/389a670a-f7fd-429e-88d6-6cb914807f1e?imageType=thumbnail","imageType":"T","sequenceNumber":6,"swiftFlag":false,"imageTypeDescription":"THUMBNAIL_IMAGE","highRes":false,"ln":992250},{"url":"https://brimages.copart.com.br/Repository/Fotos/3100ec30-925f-4292-81ee-1706366af0d8?imageType=thumbnail","imageType":"T","sequenceNumber":7,"swiftFlag":false,"imageTypeDescription":"THUMBNAIL_IMAGE","highRes":false,"ln":992250},{"url":"https://brimages.copart.com.br/Repository/Fotos/7d6ed11d-a220-4409-9ee9-4c78426df185?imageType=thumbnail","imageType":"T","sequenceNumber":8,"swiftFlag":false,"imageTypeDescription":"THUMBNAIL_IMAGE","highRes":false,"ln":992250},{"url":"https://brimages.copart.com.br/Repository/Fotos/5a79c63e-5f3f-4ced-adcc-713475c7bd31?imageType=thumbnail","imageType":"T","sequenceNumber":9,"swiftFlag":false,"imageTypeDescription":"THUMBNAIL_IMAGE","highRes":false,"ln":992250},{"url":"https://brimages.copart.com.br/Repository/Fotos/34bc9860-fadf-46a2-a283-365002140abc?imageType=thumbnail","imageType":"T","sequenceNumber":10,"swiftFlag":false,"imageTypeDescription":"THUMBNAIL_IMAGE","highRes":false,"ln":992250}],"HIGH_RESOLUTION_IMAGE":[{"url":"https://brimages.copart.com.br/Repository/Fotos/a0b0c6e4-6cb8-49ed-a1ea-6eb573f31a36","imageType":"O","sequenceNumber":1,"swiftFlag":false,"imageTypeDescription":"HIGH_RESOLUTION_IMAGE","highRes":true,"ln":992250},{"url":"https://brimages.copart.com.br/Repository/Fotos/0e96f28b-03f3-483a-969a-a442d4c6700f","imageType":"O","sequenceNumber":2,"swiftFlag":false,"imageTypeDescription":"HIGH_RESOLUTION_IMAGE","highRes":true,"ln":992250},{"url":"https://brimages.copart.com.br/Repository/Fotos/bef071aa-5500-4232-9dd3-4589cbb7b2ac","imageType":"O","sequenceNumber":3,"swiftFlag":false,"imageTypeDescription":"HIGH_RESOLUTION_IMAGE","highRes":true,"ln":992250},{"url":"https://brimages.copart.com.br/Repository/Fotos/9e741e41-18a1-4aca-92be-dee9825ac2e0","imageType":"O","sequenceNumber":4,"swiftFlag":false,"imageTypeDescription":"HIGH_RESOLUTION_IMAGE","highRes":true,"ln":992250},{"url":"https://brimages.copart.com.br/Repository/Fotos/ff04a23b-0e78-4d94-a2a1-4fd376246495","imageType":"O","sequenceNumber":5,"swiftFlag":false,"imageTypeDescription":"HIGH_RESOLUTION_IMAGE","highRes":true,"ln":992250},{"url":"https://brimages.copart.com.br/Repository/Fotos/389a670a-f7fd-429e-88d6-6cb914807f1e","imageType":"O","sequenceNumber":6,"swiftFlag":false,"imageTypeDescription":"HIGH_RESOLUTION_IMAGE","highRes":true,"ln":992250},{"url":"https://brimages.copart.com.br/Repository/Fotos/3100ec30-925f-4292-81ee-1706366af0d8","imageType":"O","sequenceNumber":7,"swiftFlag":false,"imageTypeDescription":"HIGH_RESOLUTION_IMAGE","highRes":true,"ln":992250},{"url":"https://brimages.copart.com.br/Repository/Fotos/7d6ed11d-a220-4409-9ee9-4c78426df185","imageType":"O","sequenceNumber":8,"swiftFlag":false,"imageTypeDescription":"HIGH_RESOLUTION_IMAGE","highRes":true,"ln":992250},{"url":"https://brimages.copart.com.br/Repository/Fotos/5a79c63e-5f3f-4ced-adcc-713475c7bd31","imageType":"O","sequenceNumber":9,"swiftFlag":false,"imageTypeDescription":"HIGH_RESOLUTION_IMAGE","highRes":true,"ln":992250},{"url":"https://brimages.copart.com.br/Repository/Fotos/34bc9860-fadf-46a2-a283-365002140abc","imageType":"O","sequenceNumber":10,"swiftFlag":false,"imageTypeDescription":"HIGH_RESOLUTION_IMAGE","highRes":true,"ln":992250}]}}}